compare.py
libmlxin_ext.dylib
mlxin.cpython-311-darwin.so
mlxin_data-0.0.2.dist-info/METADATA
mlxin_data-0.0.2.dist-info/WHEEL
mlxin_data-0.0.2.dist-info/top_level.txt
mlxin_data-0.0.2.dist-info/RECORD
