Metadata-Version: 2.1
Name: mlxin-data
Version: 0.0.2
Author-email: Diogo Da Cruz <diogodacruz.dev@gmail.com>
Keywords: mlx,data,png,jpeg
Requires-Python: >=3.8
Requires-Dist: mlx
